llmstudio_core/__init__.py
llmstudio_core/config.yaml
llmstudio_core/exceptions.py
llmstudio_core/providers/__init__.py
llmstudio_core/providers/azure.py
llmstudio_core/providers/bedrock_converse.py
llmstudio_core/providers/data_structures.py
llmstudio_core/providers/openai.py
llmstudio_core/providers/provider.py
llmstudio_core/providers/vertexai.py
llmstudio_core/utils.py
llmstudio_core-1.0.4.dist-info/METADATA
llmstudio_core-1.0.4.dist-info/WHEEL
llmstudio_core-1.0.4.dist-info/RECORD
