Metadata-Version: 2.3
Name: llmstudio-core
Version: 1.0.4
Summary: LLMStudio core capabilities for routing llm calls for any vendor. No proxy server required. For that use llmstudio[proxy]
License: MIT
Author: Cláudio Lemos
Author-email: claudio.lemos@tensorops.ai
Requires-Python: >=3.9,<4.0
Classifier: License :: OSI Approved :: MIT License
Classifier: Programming Language :: Python :: 3
Classifier: Programming Language :: Python :: 3.9
Classifier: Programming Language :: Python :: 3.10
Classifier: Programming Language :: Python :: 3.11
Classifier: Programming Language :: Python :: 3.12
Classifier: Programming Language :: Python :: 3.13
Requires-Dist: boto3 (>=1.35.54,<2.0.0)
Requires-Dist: openai (>=1.26,<2.0)
Requires-Dist: pydantic (>=2.5,<3.0)
Requires-Dist: pyyaml (>=6,<7)
Requires-Dist: requests (>=2.31,<3.0)
Requires-Dist: tiktoken (>=0.7,<0.8)
